shift_left/__init__.py
shift_left/cli.py
shift_left/ai/agent_factory.py
shift_left/ai/ksql_code_agent.py
shift_left/ai/process_src_tables.py
shift_left/ai/spark_sql_code_agent.py
shift_left/ai/translator_to_flink_sql.py
shift_left/ai/prompts/common/mandatory_validation.txt
shift_left/ai/prompts/common/refinement.txt
shift_left/ai/prompts/ksql_fsql/table_detection.txt
shift_left/ai/prompts/ksql_fsql/translator.txt
shift_left/ai/prompts/spark_fsql/ddl_creation.txt
shift_left/ai/prompts/spark_fsql/table_detection.txt
shift_left/ai/prompts/spark_fsql/translator.txt
shift_left/cli_commands/pipeline.py
shift_left/cli_commands/project.py
shift_left/cli_commands/table.py
shift_left/core/__init__.py
shift_left/core/compute_pool_mgr.py
shift_left/core/compute_pool_usage_analyzer.py
shift_left/core/connector_mgr.py
shift_left/core/deployment_mgr.py
shift_left/core/integration_test_mgr.py
shift_left/core/metric_mgr.py
shift_left/core/pipeline_mgr.py
shift_left/core/project_manager.py
shift_left/core/statement_mgr.py
shift_left/core/table_mgr.py
shift_left/core/test_mgr.py
shift_left/core/models/__init__.py
shift_left/core/models/flink_compute_pool_model.py
shift_left/core/models/flink_statement_model.py
shift_left/core/models/flink_test_model.py
shift_left/core/templates/.env_tmpl
shift_left/core/templates/.gitignore_tmpl
shift_left/core/templates/basic_test_readme_template.md
shift_left/core/templates/common.mk
shift_left/core/templates/config_tmpl.yaml
shift_left/core/templates/create_table_skeleton.jinja
shift_left/core/templates/dedup_dml_skeleton.jinja
shift_left/core/templates/dml_src_tmpl.jinja
shift_left/core/templates/itg_test_readme.jinja
shift_left/core/templates/makefile_ddl_dml_tmpl.jinja
shift_left/core/templates/min_config_tmpl.yaml
shift_left/core/templates/set_env_temp
shift_left/core/templates/test_dedup_statement.jinja
shift_left/core/templates/tracking_tmpl.jinja
shift_left/core/templates/validate_test.jinja
shift_left/core/utils/__init__.py
shift_left-0.1.47.dist-info/METADATA
shift_left-0.1.47.dist-info/WHEEL
shift_left-0.1.47.dist-info/entry_points.txt
shift_left-0.1.47.dist-info/RECORD
