Metadata-Version: 2.4
Name: shift_left
Version: 0.1.47
Summary: The shift-left CLI to manage your shift-left project
Project-URL: Homepage, https://jbcodeforce.github.io/shift_left_utils/
Project-URL: Repository, https://github.com/jbcodeforce/shift_left_utils
Project-URL: Documentation, https://jbcodeforce.github.io/shift_left_utils/
Project-URL: Issues, https://github.com/jbcodeforce/shift_left_utils/issues
Author-email: jbcodeforce <jerome.boyer@gmail.com>
License: Apache-2.0
Keywords: cli,confluent,data-pipeline,flink,kafka,migration,sql,streaming
Classifier: Development Status :: 4 - Beta
Classifier: Environment :: Console
Classifier: Intended Audience :: Developers
Classifier: License :: OSI Approved :: Apache Software License
Classifier: Programming Language :: Python :: 3
Classifier: Programming Language :: Python :: 3.12
Classifier: Topic :: Database
Classifier: Topic :: Software Development :: Code Generators
Requires-Python: <3.13,>=3.12
Requires-Dist: click<8.2.0
Requires-Dist: confluent-kafka>=2.10.0
Requires-Dist: jinja2==3.1.6
Requires-Dist: matplotlib>=3.10.1
Requires-Dist: mcp>=1.16.0
Requires-Dist: networkx>=3.4.2
Requires-Dist: openai>=1.97.1
Requires-Dist: pydantic-yaml>=1.4.0
Requires-Dist: pydantic>=2.6.10
Requires-Dist: pytz>=2025.2
Requires-Dist: pyyaml>=6.0.2
Requires-Dist: requests>=2.32.3
Requires-Dist: rich>=13.9.4
Requires-Dist: sqlglot>=27.19.0
Requires-Dist: toml>=0.10.2
Requires-Dist: typer>=0.15.2
Provides-Extra: dev
Requires-Dist: pytest>=8.3.5; extra == 'dev'
